{"template":"/home/maxiee/Code/Blog/maxiee.github.io/src/pages/post","sharedHashesByProp":{},"data":{"post":{"name":"Maxiee 的 2019.05 月度总结","desc":"Maxiee 的 5 月份总结。","type":"md","link":"Maxiee201905md","create":"2019-06-06","filename":"Maxiee2019.05.md"},"content":"## 知识管理软件\n\n5 月份我大部分业余精力都在开发一个知识管理软件。这是因为我曾经尝试过许多笔记、Wiki 软件，但没有一个能够满足我的需要。我曾经也自己开发过几个笔记软件，但也无法令自己满意。\n\n我一直都处在对知识的焦虑当中，哪些没有学会的知识、没有读过的书，常年累月地折磨着我。\n\n我想我只有一种情况能够战胜这种焦虑，那就是通过工具增进自己的认知能力，具备学会这些知识的能力。\n\n因此，在 2019 年 5 月份，我又踏上了开发知识管理软件的征程。\n\n与以往的尝试相比，这一次的不同之处在于，经过一年多的历练，我的技术水平有了长足的提升，很多以前能力不及的，现在都能胜任了。\n\n## 知识图谱\n\n现有的笔记软件对于文档的组织能力是比较弱的。\n\n不论是使用树进行组织，还是通过 Org 进行组织，或者是通过 Tag 进行组织，他们都无法将知识体系完整地表达出来。\n\n在这一点上做得最好的是维基百科，而它背后的知识管理模式可以被看做是一种知识图谱的实现，因此我展开了对知识图谱的学习。\n\n通过学习我发现知识图谱理论正是我的知识管理软件所需要的组织方式。\n\n知识图谱理论所包含的能力远远不仅于此，它还能够根据你的 Knowledge Base 将隐式的知识显化出来，或者通过推理来帮你\"想\"出 Knowledge Base 中没有的知识。\n\n我设计了一个短期一个长期方案：\n\n- 短期：使用知识图谱进行文档组织、可视化表示，同时保持未来扩展性\n- 长期：深入学习知识图谱理论，并展开应用\n\n## 网站改版\n\n5 月一直想进行网站改版，奈何精力有限一直排不上。\n\n改版的原因是下半年我写博客的时间会变少，我希望有一种更轻量级的分享方式。\n\n目前构思的是像湾区评论那样上一个文章点评的板块。\n\n## 学车\n\n6 月份每个周末都要去学车，占据了比较多的精力。\n\n人到了 30 岁的年纪，属于自己的时间会越来越少。\n\n多年以前，周末时光是我最好的朋友，现在我发现，每天清晨的时光成了我最好的朋友。\n\n## 展望\n\n进入六月了，知识管理软件已经具备初步的知识图谱功能，我希望能够基于它建立一个让我满意的知识体系，同时验证这种方式对我的学习效果有没有提升效果。"},"path":"post/Maxiee201905md"}
